ipcqueue-0.9.7.dist-info/RECORD
ipcqueue-0.9.7.dist-info/top_level.txt
ipcqueue-0.9.7.dist-info/WHEEL
ipcqueue-0.9.7.dist-info/METADATA
ipcqueue-0.9.7.dist-info/LICENSE
ipcqueue-0.9.7.dist-info/AUTHORS
ipcqueue/sysvmq.py
ipcqueue/serializers.py
ipcqueue/posixmq.py
ipcqueue/_sysvmq.abi3.so
ipcqueue/_posixmq.abi3.so
ipcqueue/__init__.py
