Metadata-Version: 2.1
Name: ipcqueue
Version: 0.9.7
Summary: Ipcqueue provides POSIX and SYS V message queues functionality to exchange data among processes.
Home-page: https://github.com/seifert/ipcqueue
Author: Jan Seifert
Author-email: jan.seifert@fotkyzcest.net
License: BSD
Keywords: sysv posix ipc queue
Platform: UNKNOWN
Classifier: Programming Language :: Python :: 2.7
Classifier: Programming Language :: Python :: 3.4
Classifier: Programming Language :: Python :: 3.5
Classifier: Programming Language :: Python :: 3.6
Classifier: License :: OSI Approved :: BSD License
Classifier: Operating System :: POSIX
Classifier: Development Status :: 4 - Beta
Classifier: Intended Audience :: Developers
Classifier: Topic :: Software Development :: Libraries :: Python Modules
License-File: LICENSE
License-File: AUTHORS
Requires-Dist: cffi (>=1)
